odoo/addons/base_user_copy_user_role/README.rst
odoo/addons/base_user_copy_user_role/__init__.py
odoo/addons/base_user_copy_user_role/__manifest__.py
odoo/addons/base_user_copy_user_role/security/ir.model.access.csv
odoo/addons/base_user_copy_user_role/static/description/icon.png
odoo/addons/base_user_copy_user_role/wizards/__init__.py
odoo/addons/base_user_copy_user_role/wizards/base_copy_user_role.py
odoo/addons/base_user_copy_user_role/wizards/base_copy_user_role.xml
odoo14_addon_base_user_copy_user_role-14.0.1.0.1.dist-info/METADATA
odoo14_addon_base_user_copy_user_role-14.0.1.0.1.dist-info/WHEEL
odoo14_addon_base_user_copy_user_role-14.0.1.0.1.dist-info/top_level.txt
odoo14_addon_base_user_copy_user_role-14.0.1.0.1.dist-info/RECORD
